yatla/__init__.py
yatla/_parser.py
yatla/ast_nodes.py
yatla/builtins.py
yatla/lexer.py
yatla/main.py
yatla/validation.py
yatla-0.4.0.dist-info/LICENSE
yatla-0.4.0.dist-info/METADATA
yatla-0.4.0.dist-info/WHEEL
yatla-0.4.0.dist-info/entry_points.txt
yatla-0.4.0.dist-info/RECORD
