Metadata-Version: 2.1
Name: yatla
Version: 0.4.0
Summary: A templating engine with a simple templating language specifically designed for type inference, allowing consumers to provide users with slots of determined types.
License: MIT
Author: Eugene Prout
Author-email: eugene.prout1@gmail.com
Requires-Python: >=3.10,<4.0
Classifier: License :: OSI Approved :: MIT License
Classifier: Programming Language :: Python :: 3
Classifier: Programming Language :: Python :: 3.10
Classifier: Programming Language :: Python :: 3.11
Classifier: Programming Language :: Python :: 3.12
Requires-Dist: click (>=8.1.7,<9.0.0)
